du_v2/__init__.py
du_v2/du_v2.py
du_v2-0.1.0.dist-info/LICENSE
du_v2-0.1.0.dist-info/METADATA
du_v2-0.1.0.dist-info/WHEEL
du_v2-0.1.0.dist-info/entry_points.txt
du_v2-0.1.0.dist-info/top_level.txt
du_v2-0.1.0.dist-info/RECORD
