Metadata-Version: 2.1
Name: du_v2
Version: 0.1.0
Summary: More useful version of du
Home-page: https://github.com/tylerlum/du_v2
Author: Tyler Lum
Author-email: tylergwlum@gmail.com
Classifier: Intended Audience :: Developers
Classifier: License :: OSI Approved :: MIT License
Classifier: Programming Language :: Python :: 3
Requires-Python: >=3.8
License-File: LICENSE
Requires-Dist: tyro
Requires-Dist: tqdm
